Metadata-Version: 1.2
Name: rss2toot
Version: 0.0.2
Summary: Toot emitter from RSS feed using Mastodon.py
Home-page: https://gitlab.com/petzah/rss2toot
Author: Peter Zahradnik
Author-email: petzah+rss2toot@znik.sk
License: MIT
Keywords: rss mastodon toot
Platform: UNKNOWN
Classifier: Development Status :: 3 - Alpha
Classifier: Intended Audience :: Developers
Classifier: Topic :: Communications
Classifier: License :: OSI Approved :: MIT License
Classifier: Programming Language :: Python :: 3.5
Requires-Python: >=3.5
